commen/__init__.py
commen/__main__.py
commen/init_project.py
commen/setup_run.py
commen/unit_apache_beam.py
commen/unit_dict.py
commen/unit_encryption.py
commen/unit_fun.py
commen/unit_logger.py
commen/unit_request.py
commen/unit_tasks.py
commen/常用命令.py
commen/case_project/__init__.py
commen/case_project/base_project.py
commen/case_project/json_coder.py
commen/case_project/setup_set.py
commen/case_project/version.py
commen/testcase/__init__.py
commen/testcase/apache/__init__.py
commen/testcase/apache/beam_class.py
commen/testcase/apache/data.py
commen/testcase/apache/par_do.py
commen/testcase/apache/test_cogroupbykey.py
commen/testcase/apache/test_file.py
commen/testcase/apache/test_fiter.py
commen/testcase/apache/test_flatmap.py
commen/testcase/apache/test_map.py
commen/testcase/apache/test_par_do.py
commen/testcase/apache/test_regex.py
commen/testcase/apache/test_time.py
commen/testcase/apache/test_to_string.py
huhangkai-1.5.5.dist-info/METADATA
huhangkai-1.5.5.dist-info/WHEEL
huhangkai-1.5.5.dist-info/entry_points.txt
huhangkai-1.5.5.dist-info/top_level.txt
huhangkai-1.5.5.dist-info/RECORD
